binigogeo/__init__.py
binigogeo/core.py
binigogeo/exceptions.py
binigogeo/hyperplane.py
binigogeo/random.py
binigogeo/ray.py
binigogeo/segment.py
binigogeo/typing.py
binigogeo/utils.py
binigogeo-0.0.5.dist-info/licenses/LICENSE
binigogeo-0.0.5.dist-info/METADATA
binigogeo-0.0.5.dist-info/WHEEL
binigogeo-0.0.5.dist-info/top_level.txt
binigogeo-0.0.5.dist-info/RECORD
