Metadata-Version: 2.4
Name: binigogeo
Version: 0.0.5
Summary: 2D and 3D geometry in Python.
Author: Benjamin D. Killeen with contributions from Blanca
Author-email: binigo1@jhu.edu
License: MIT
Requires-Python: >=3.10
License-File: LICENSE
Requires-Dist: numpy
Requires-Dist: scipy
Requires-Dist: typing_extensions
Dynamic: author
Dynamic: author-email
Dynamic: description
Dynamic: description-content-type
Dynamic: license
Dynamic: license-file
Dynamic: requires-dist
Dynamic: requires-python
Dynamic: summary
